{
  "hash": "499e665badd4344d7a4029224d50ae5d",
  "result": {
    "markdown": "---\ntitle: \"Sam's blood counts\"\nsubtitle: \"Round 2 of chemotherapy\"\ndate: today\nformat:\n  html: default\n  pdf: default\nknitr: \n  opts_chunk: \n    eval: false\n    message: false\n    warning: false\n    echo: false\ncode-fold: true\neditor_options: \n  chunk_output_type: console\n---\n\n\n\n\nData has been provided daily by the medical team here at BC Children's Hospital. Day 0, May 12, 2023, was the start of Sam's second round of chemotherapy.\n\n\n::: {.cell}\n\n:::\n\n::: {.cell}\n\n:::\n\n\n![Blood counts from chemo round 2](https://samsstory.s3.ca-central-1.amazonaws.com/blood_graph.png)\n",
    "supporting": [],
    "filters": [
      "rmarkdown/pagebreak.lua"
    ],
    "includes": {},
    "engineDependencies": {},
    "preserve": {},
    "postProcess": true
  }
}